TheMathModule/__init__.py
TheMathModule/avg_or_mean.py
TheMathModule-0.2.0.dist-info/METADATA
TheMathModule-0.2.0.dist-info/WHEEL
TheMathModule-0.2.0.dist-info/top_level.txt
TheMathModule-0.2.0.dist-info/RECORD
